logfire_callback/__init__.py
logfire_callback/callback.py
logfire_callback-1.0.0.dist-info/METADATA
logfire_callback-1.0.0.dist-info/WHEEL
logfire_callback-1.0.0.dist-info/licenses/LICENSE
logfire_callback-1.0.0.dist-info/RECORD
