Metadata-Version: 2.4
Name: logfire-callback
Version: 1.0.0
Summary: A callback for logging training events from Hugging Face's Transformers to Logfire 🤗
Project-URL: Homepage, https://github.com/louisbrulenaudet/logfire-callback
Project-URL: Repository, https://github.com/louisbrulenaudet/logfire-callback
Project-URL: Issues, https://github.com/louisbrulenaudet/logfire-callback/issues
Author-email: Louis Brulé Naudet <contact@louisbrulenaudet.com>
Maintainer-email: Louis Brulé Naudet <contact@louisbrulenaudet.com>
License-Expression: Apache-2.0
License-File: LICENSE
Keywords: callback,huggingface,logfire,logging,trainer,transformers
Classifier: Development Status :: 4 - Beta
Classifier: Intended Audience :: Developers
Classifier: License :: OSI Approved :: Apache Software License
Classifier: Programming Language :: Python :: 3
Classifier: Programming Language :: Python :: 3.11
Requires-Python: >=3.11
Requires-Dist: logfire>=3.9.0
Requires-Dist: transformers>=4.49.0
Provides-Extra: dev
Requires-Dist: pre-commit-uv>=4.1.4; extra == 'dev'
Requires-Dist: pre-commit>=4.1.0; extra == 'dev'
Requires-Dist: pyright>=1.1.392.post0; extra == 'dev'
Requires-Dist: pytest-cov>=4.1.0; extra == 'dev'
Requires-Dist: pytest>=8.3.4; extra == 'dev'
Requires-Dist: ruff>=0.9.3; extra == 'dev'
